bmp_transcode/__init__.py
bmp_transcode-0.3.0.dist-info/DESCRIPTION.rst
bmp_transcode-0.3.0.dist-info/METADATA
bmp_transcode-0.3.0.dist-info/RECORD
bmp_transcode-0.3.0.dist-info/WHEEL
bmp_transcode-0.3.0.dist-info/entry_points.txt
bmp_transcode-0.3.0.dist-info/metadata.json
bmp_transcode-0.3.0.dist-info/top_level.txt
