Metadata-Version: 2.0
Name: bmp-transcode
Version: 0.3.0
Summary: Transcode orindary files to and from bitmap images.
Home-page: https://github.com/nvllsvm/bmp-transcode
Author: Andrew Rabert
Author-email: arabert@nullsum.net
License: Apache 2.0
Platform: UNKNOWN
Classifier: Development Status :: 4 - Beta
Classifier: Intended Audience :: End Users/Desktop
Classifier: License :: OSI Approved :: Apache Software License
Classifier: Programming Language :: Python :: 3 :: Only
Requires-Dist: pillow
